Metadata-Version: 2.1
Name: ferramentas
Version: 1.0
Summary: ahuashuahus
Author: Daniel
Author-email: daniel@gmail.com
Keywords: camera,video,processamento
License-File: license.txt
